Metadata-Version: 2.1
Name: atd-agolutil
Version: 0.0.2
Summary: Python utilities interacting with the ArcGIS Online (AGOL) API.
Home-page: https://github.com/cityofaustin/atd-data-utils-agol
Author: City of Austin
Author-email: transportation.data@austintexas.gov
License: UNKNOWN
Platform: UNKNOWN
Classifier: Programming Language :: Python :: 3
Classifier: License :: Public Domain
Classifier: Operating System :: OS Independent
Classifier: Development Status :: 4 - Beta
